Metadata-Version: 1.0
Name: ltp-eval
Version: 0.3
Summary: Query your results
Home-page: https://gitlab.com/famorim/ltp_eval.git
Author: LTP
Author-email: franciscoamorim@ltplabs.com
License: LTP
Platform: UNKNOWN
